<?xml version="1.0" encoding="UTF-8"?>
<odoo>
    <data>
        <record model="ir.ui.view" id="res_company_trial_form">
        	<field name="name">res_company_trial.form</field>
        	<field name="model">res.company</field>
        	<field name="inherit_id" ref="base.view_company_form"/>
        	<field name="arch" type="xml">
        		<div class="oe_title" position="after">
                    <group>
    					<field name="is_trial"/>
    					<field name="trial_exp"/>
                    </group>
				</div>
        	</field>
        </record>
    </data>
</odoo>